pystematic_torch/__init__.py
pystematic_torch/context.py
pystematic_torch/recording.py
pystematic_torch/torch_plugin.py
pystematic_torch/utils.py
pystematic_torch-1.3.4.dist-info/entry_points.txt
pystematic_torch-1.3.4.dist-info/LICENSE
pystematic_torch-1.3.4.dist-info/WHEEL
pystematic_torch-1.3.4.dist-info/METADATA
pystematic_torch-1.3.4.dist-info/RECORD
