Metadata-Version: 2.1
Name: pystematic-torch
Version: 1.3.4
Summary: Pystematic extension for running experiments in pytorch.
Home-page: https://github.com/evalldor/pystematic-torch
License: MIT
Author: E.Valldor
Requires-Python: >=3.6.2,<4.0.0
Classifier: Development Status :: 5 - Production/Stable
Classifier: Intended Audience :: Science/Research
Classifier: License :: OSI Approved :: MIT License
Classifier: Operating System :: OS Independent
Classifier: Programming Language :: Python
Classifier: Programming Language :: Python :: 3
Classifier: Programming Language :: Python :: 3.7
Classifier: Programming Language :: Python :: 3.8
Classifier: Programming Language :: Python :: 3.9
Classifier: Programming Language :: Python :: 3.10
Classifier: Programming Language :: Python :: 3.11
Classifier: Topic :: Scientific/Engineering
Requires-Dist: importlib-metadata (>=4.6.4,<5.0.0)
Requires-Dist: matplotlib (>=3.0,<4.0)
Requires-Dist: protobuf (<=3.20.1)
Requires-Dist: pystematic (>=1.5.0,<2.0.0)
Requires-Dist: tensorboardX (>=2.4,<3.0)
Requires-Dist: torch (>=1.8,<2.0)
Requires-Dist: tqdm (>=4.62.1,<5.0.0)
Requires-Dist: wrapt (>=1.12.1,<2.0.0)
Project-URL: Repository, https://github.com/evalldor/pystematic-torch
